odoo8_addon_website_sale_require_login-8.0.1.0.0.99.dev8-py2.7-nspkg.pth
odoo8_addon_website_sale_require_login-8.0.1.0.0.99.dev8.dist-info/top_level.txt
odoo8_addon_website_sale_require_login-8.0.1.0.0.99.dev8.dist-info/WHEEL
odoo8_addon_website_sale_require_login-8.0.1.0.0.99.dev8.dist-info/RECORD
odoo8_addon_website_sale_require_login-8.0.1.0.0.99.dev8.dist-info/metadata.json
odoo8_addon_website_sale_require_login-8.0.1.0.0.99.dev8.dist-info/DESCRIPTION.rst
odoo8_addon_website_sale_require_login-8.0.1.0.0.99.dev8.dist-info/METADATA
odoo8_addon_website_sale_require_login-8.0.1.0.0.99.dev8.dist-info/namespace_packages.txt
odoo_addons/website_sale_require_login/__openerp__.py
odoo_addons/website_sale_require_login/__init__.py
odoo_addons/website_sale_require_login/README.rst
odoo_addons/website_sale_require_login/i18n/it.po
odoo_addons/website_sale_require_login/i18n/es.po
odoo_addons/website_sale_require_login/i18n/sl.po
odoo_addons/website_sale_require_login/views/website_sale.xml
odoo_addons/website_sale_require_login/views/assets.xml
odoo_addons/website_sale_require_login/controllers/main.py
odoo_addons/website_sale_require_login/controllers/__init__.py
odoo_addons/website_sale_require_login/static/description/icon.png
odoo_addons/website_sale_require_login/static/src/js/website_sale_tour_buy_login.js
