Metadata-Version: 2.0
Name: odoo8-addon-website-sale-require-login
Version: 8.0.1.0.0.99.dev8
Summary: Force users to login for buying
Home-page: http://www.antiun.com
Author: Antiun Ingeniería, S.L., Odoo Community Association (OCA)
Author-email: support@odoo-community.org
License: AGPL-3
Platform: UNKNOWN
Requires-Dist: odoo (<9.0a,>=8.0a)
Requires-Dist: odoo8-addon-website-sale-suggest-create-account
Classifier: Programming Language :: Python :: 2.7
Classifier: Framework :: Odoo
Classifier: License :: OSI Approved :: GNU Affero General Public License v3
